thymiodirect/__init__.py
thymiodirect/assembler.py
thymiodirect/connection.py
thymiodirect/message.py
thymiodirect/thymio.py
ThymioDirect_EPFL_Mobots-0.1.0.dist-info/LICENSE
ThymioDirect_EPFL_Mobots-0.1.0.dist-info/METADATA
ThymioDirect_EPFL_Mobots-0.1.0.dist-info/WHEEL
ThymioDirect_EPFL_Mobots-0.1.0.dist-info/top_level.txt
ThymioDirect_EPFL_Mobots-0.1.0.dist-info/RECORD
