Metadata-Version: 2.1
Name: ThymioDirect-EPFL-Mobots
Version: 0.1.0
Summary: Communication with Thymio II robot via serial port or TCP
Home-page: https://github.com/epfl-mobots/thymio-python
Author: Yves Piguet
License: UNKNOWN
Platform: UNKNOWN
Classifier: Programming Language :: Python :: 3
Classifier: License :: OSI Approved :: BSD License
Classifier: Intended Audience :: Education
Classifier: Framework :: AsyncIO
Requires-Python: >=3.6
Requires-Dist: pyserial
